nonogram/__init__.py
nonogram/analysis.py
nonogram_analysis-1.0.1.dist-info/METADATA
nonogram_analysis-1.0.1.dist-info/WHEEL
nonogram_analysis-1.0.1.dist-info/top_level.txt
nonogram_analysis-1.0.1.dist-info/RECORD
