Metadata-Version: 2.1
Name: nonogram-analysis
Version: 1.0.1
Summary: Nonogram Game Session Analysis
Home-page: UNKNOWN
Author: Daniel CAUNE
Author-email: daniel.caune@gmail.com
License: MIT
Platform: any
Classifier: Development Status :: 5 - Production/Stable
Classifier: License :: OSI Approved :: MIT License
Classifier: Operating System :: OS Independent
Classifier: Programming Language :: Python
Classifier: Topic :: Software Development :: Libraries
Requires-Python: >=3.6
Requires-Dist: pytest
Requires-Dist: twine
Requires-Dist: setuptools
Requires-Dist: wheel
Requires-Dist: pipfile
